kid_ppg/__init__.py
kid_ppg/adaptive_linear_model.py
kid_ppg/kid_ppg.py
kid_ppg/preprocessing.py
kid_ppg/demo/__init__.py
kid_ppg/demo/demo_utils.py
kid_ppg/demo/demo_data/PPGDalia_S6_stairs.pkl
kid_ppg/demo/demo_data/__init__.py
kid_ppg/model_weights/__init__.py
kid_ppg/model_weights/kid_ppg_weights.h5
kid_ppg-0.0.4.dist-info/METADATA
kid_ppg-0.0.4.dist-info/WHEEL
kid_ppg-0.0.4.dist-info/licenses/LICENSE
kid_ppg-0.0.4.dist-info/RECORD
