Metadata-Version: 2.3
Name: kid_ppg
Version: 0.0.4
Summary: A library for performing probabilistic heart rate extraction from photoplehysmography signals.
Project-URL: Homepage, https://github.com/esl-epfl/KID-PPG
Author-email: Christodoulos Kechris <christodoulos.kechris@epfl.ch>
License-File: LICENSE
Classifier: License :: OSI Approved :: GNU General Public License v3 (GPLv3)
Classifier: Operating System :: OS Independent
Classifier: Programming Language :: Python :: 3
Requires-Python: ==3.10.8
Requires-Dist: numpy==1.24.3
Requires-Dist: scipy==1.12.0
Requires-Dist: silence-tensorflow==1.2.1
Requires-Dist: tensorflow-probability==0.20.1
Requires-Dist: tensorflow==2.13.0
